graphkit/__init__.py
graphkit/graph.py
graphkit/algorithms/__init__.py
graphkit/algorithms/connectivity/kosaraju.py
graphkit/algorithms/mst/__init__.py
graphkit/algorithms/mst/kruskal.py
graphkit/algorithms/mst/prim.py
graphkit/algorithms/shortest_path/__init__.py
graphkit/algorithms/shortest_path/bellman_ford.py
graphkit/algorithms/shortest_path/dijkstra.py
graphkit/algorithms/shortest_path/floyd_warshall.py
graphkit/algorithms/traversal/__init__.py
graphkit/algorithms/traversal/bfs.py
graphkit/algorithms/traversal/dfs.py
graphkit/algorithms/traversal/topological_sort.py
graphkit/flow/__init__.py
graphkit/flow/dinic.py
graphkit/utils/__init__.py
graphkit/utils/union_find.py
pygraphkit-1.0.0.dist-info/licenses/LICENSE
pygraphkit-1.0.0.dist-info/METADATA
pygraphkit-1.0.0.dist-info/WHEEL
pygraphkit-1.0.0.dist-info/top_level.txt
pygraphkit-1.0.0.dist-info/RECORD
