Metadata-Version: 2.4
Name: pygraphkit
Version: 1.0.0
Summary: A clean and reusable graph algorithms toolkit
Author: Gaurav Khakse
License: MIT
Requires-Python: >=3.9
License-File: LICENSE
Dynamic: license-file
